aionap/__init__.py
aionap/exceptions.py
aionap/serialize.py
aionap/utils.py
aionap-0.7.dist-info/LICENSE
aionap-0.7.dist-info/METADATA
aionap-0.7.dist-info/WHEEL
aionap-0.7.dist-info/top_level.txt
aionap-0.7.dist-info/RECORD
