Metadata-Version: 2.1
Name: aionap
Version: 0.7
Summary: Python Asyncio REST Client
Home-page: https://github.com/chassing/aionap
Author: Christian Assing
Author-email: chris@ca-net.org
License: UNKNOWN
Platform: UNKNOWN
Classifier: Development Status :: 2 - Pre-Alpha
Classifier: Programming Language :: Python
Classifier: Programming Language :: Python :: 3
Classifier: Programming Language :: Python :: 3.6
Requires-Dist: aiohttp
